[
    {
        "@id": "https://github.com/nakamura196/amami/raw/master/docs/iiif/amami/canvas/p342#xywh=1968,3449,42,25",
        "@type": "sc:Canvas",
        "label": "Google Cloud Vision API",
        "metadata": [
            {
                "label": "Text",
                "value": "|19"
            }
        ]
    },
    {
        "@id": "https://github.com/nakamura196/amami/raw/master/docs/iiif/amami/canvas/p342#xywh=1730,41,316,79",
        "@type": "sc:Canvas",
        "label": "Google Cloud Vision API",
        "metadata": [
            {
                "label": "Text",
                "value": "Black©Kodak,2007TM:Kodak3/Color"
            }
        ]
    },
    {
        "@id": "https://github.com/nakamura196/amami/raw/master/docs/iiif/amami/canvas/p342#xywh=1880,3447,47,27",
        "@type": "sc:Canvas",
        "label": "Google Cloud Vision API",
        "metadata": [
            {
                "label": "Text",
                "value": "118"
            }
        ]
    },
    {
        "@id": "https://github.com/nakamura196/amami/raw/master/docs/iiif/amami/canvas/p342#xywh=1642,760,298,292",
        "@type": "sc:Canvas",
        "label": "Google Cloud Vision API",
        "metadata": [
            {
                "label": "Text",
                "value": "際的に見ても最近派出姉の増加は夥しいもので、東京市内外女で約八千人と希されてみるが何不足の有様である。東京の派出婚組合では料理店、待合、旅館、カフェ!等に派出を許可され度いと修練に延期してのるが共れが許可になれば派出始等の將來は震に有望なものがあらう。東京市內外にある共等多の派出端組合の中でも良質の派出姉を出すので最も評判のある"
            }
        ]
    },
    {
        "@id": "https://github.com/nakamura196/amami/raw/master/docs/iiif/amami/canvas/p342#xywh=1726,1106,217,277",
        "@type": "sc:Canvas",
        "label": "Google Cloud Vision API",
        "metadata": [
            {
                "label": "Text",
                "value": "才以上20名以下の方々です。若い方には御嫁入金を自分で貯めようといふ人、中年以上の方には未亡人が多く、愛子の驚めに稼がれてる感心な人々っ。中にいある身で生活費の一助に働いてみる向もあります。之を割合ひ申しますと未婚者が五割甘つて結婚した事のある者!三割、有夫者が二つです。牧入は食事付で二十五回から"
            }
        ]
    },
    {
        "@id": "https://github.com/nakamura196/amami/raw/master/docs/iiif/amami/canvas/p342#xywh=1571,1421,374,298",
        "@type": "sc:Canvas",
        "label": "Google Cloud Vision API",
        "metadata": [
            {
                "label": "Text",
                "value": "法律特許事務開始久留義船…小生今回法律特許事務所を開設し一意専弁護士並に辨理士事務に従事する事に相成候間左様御了知被遊度就ては夫々熱棘なる塚門者を置き一般刑事民事商事は勿論鐵道調係諸率務をち取扱可申候條何卒事件の大小に拘らず御用仰付被遊度……(十一月廿二日)東京府巣鴨町一丁目六拾九番地(岩家分譲地俗稱大和郷有線巣購、市電西丸町下車)ハ昭法律特許事務所電話大(8)一九一番市酸道局長前眾議院議員義"
            }
        ]
    },
    {
        "@id": "https://github.com/nakamura196/amami/raw/master/docs/iiif/amami/canvas/p342#xywh=1674,2656,268,291",
        "@type": "sc:Canvas",
        "label": "Google Cloud Vision API",
        "metadata": [
            {
                "label": "Text",
                "value": "千九百五十年となる。斯の如き異常なる歴史を有することは、吾等の組先の間に山獄崇敬の念が如何に深かつたかを示すもので、又木花咲耶姫命の御父大山祇神が山嶽主宰の神であり、諸種の事蹟を綜合して神が富士山麓に居住し、主として此の山を統宰せられたこと~結つて富士は秀麗千古に比な姫が生育の地であることに想到せば、毎崇二千年の久しをに亘るも宜なる哉と肯かれるところである。"
            }
        ]
    },
    {
        "@id": "https://github.com/nakamura196/amami/raw/master/docs/iiif/amami/canvas/p342#xywh=1789,2251,7,23",
        "@type": "sc:Canvas",
        "label": "Google Cloud Vision API",
        "metadata": [
            {
                "label": "Text",
                "value": "teen"
            }
        ]
    },
    {
        "@id": "https://github.com/nakamura196/amami/raw/master/docs/iiif/amami/canvas/p342#xywh=1613,3450,46,25",
        "@type": "sc:Canvas",
        "label": "Google Cloud Vision API",
        "metadata": [
            {
                "label": "Text",
                "value": "115"
            }
        ]
    },
    {
        "@id": "https://github.com/nakamura196/amami/raw/master/docs/iiif/amami/canvas/p342#xywh=1530,90,109,30",
        "@type": "sc:Canvas",
        "label": "Google Cloud Vision API",
        "metadata": [
            {
                "label": "Text",
                "value": "White"
            }
        ]
    },
    {
        "@id": "https://github.com/nakamura196/amami/raw/master/docs/iiif/amami/canvas/p342#xywh=1498,1365,126,18",
        "@type": "sc:Canvas",
        "label": "Google Cloud Vision API",
        "metadata": [
            {
                "label": "Text",
                "value": "家氏:山梨"
            }
        ]
    },
    {
        "@id": "https://github.com/nakamura196/amami/raw/master/docs/iiif/amami/canvas/p342#xywh=1502,1516,111,33",
        "@type": "sc:Canvas",
        "label": "Google Cloud Vision API",
        "metadata": [
            {
                "label": "Text",
                "value": "法成無理して、"
            }
        ]
    },
    {
        "@id": "https://github.com/nakamura196/amami/raw/master/docs/iiif/amami/canvas/p342#xywh=1191,1997,751,308",
        "@type": "sc:Canvas",
        "label": "Google Cloud Vision API",
        "metadata": [
            {
                "label": "Text",
                "value": "戦の結果は確か一点の差で同志社側の勝利となり、ワット手を上げた早大生さて眺めて歌にも同志社の校歌を知らないのでその「都の西北、早務用の杜にと早稲田の校歌で同志社の方を唱えた。――と近頃愉快な應援スポーツマンシツブであった。共応で共の天時なスポーツマンシップを發揮せしめ都下大新聞の蓋を博した南長森山君は我が大島の出身、森山北紺屋署長の令息なのである。同君は目下早大法學部二年に在喫中で、駅業の休暇あらゆる運動競技に、母校の名譽の爲めに常に先頭に立つて、熱狂する應援團を指揮統卒してみる、熱血鬼である。早大があらゆる運動競技に向五所敵なく断然、日本の親権を掌握し、所謂、運動王國を出現せしめてみるも、つまり森山若の様な猛烈な魅援者がある為めで其の点に於て森山君の双縦たるものは魯に大なるものがある。お父さんが「そんなに運動の方にばかり夢中になつては、勉強がロクに出来ない。その方はもうよい加減にして、勉強に集中する構に……」と溫い親心の心配のあまり云はれると。同君は「いやお父さん勿論勉強は致して居ます。決して學業をおろそかにして居ません。どうぞ御安心して下さい。私はこの光跡ある早稲田の歴史を世界に發揚せしめる盛めにどうしてもやらざるを得ないのです。日本"
            }
        ]
    },
    {
        "@id": "https://github.com/nakamura196/amami/raw/master/docs/iiif/amami/canvas/p342#xywh=1222,2323,718,297",
        "@type": "sc:Canvas",
        "label": "Google Cloud Vision API",
        "metadata": [
            {
                "label": "Text",
                "value": "軍が、向う所敵なく、ドット突進の出來るのもつまり背後に、根掘宮八千萬の同胞が熱烈なる壁授と断りがある為めでせう。延動競技もそれと同様で、選手,勝敗は質に魅授の如何にあると云つても過言ではないのです。それ故、どう態援する事丈けは御許し下さい……」と答へられたとの事、同岩は置に御本人が云つて居られる如く、全く美はし母校愛のかたまりであると云つてもよい。同君の火の出る様な魅援振りは、皆に涙ぐましい程である。だが、熱狂の餘りや、ともすればそり易い中劣なる彌次や醜い魅援は断じて君のなさない所で如何に正正堂々と分別をわきまへて終始しているかといふ事は、災に都下大新聞の賞該したことに依つて裏書されてみる。同料は極めて不屈かく無ければならぬと自分の信じた事は断々乎として決行するの男に富んでおる。その風貌、其の性格イタリーの傑ムッソリューに酷似してねるといヘば流し、思ひ半ばに過ぐるものがあらう。同君は魅援團長として早稲田に雪くのみでなく、又全國の男を描る早大ボート部選手として共の名を歌はれてゐる。學業にも動に熱心なる如く、大の勉ヨ家で常に俊秀の成績を示しておるので要文間に革をなしてる尚範秀君は英に二科展に出品して再度入選の光業を有する若き藝術家泉二勝憾君とは錦城中學時代からの御友達で今でも大の仲好であ"
            }
        ]
    },
    {
        "@id": "https://github.com/nakamura196/amami/raw/master/docs/iiif/amami/canvas/p342#xywh=1545,1585,14,3",
        "@type": "sc:Canvas",
        "label": "Google Cloud Vision API",
        "metadata": [
            {
                "label": "Text",
                "value": "大"
            }
        ]
    },
    {
        "@id": "https://github.com/nakamura196/amami/raw/master/docs/iiif/amami/canvas/p342#xywh=1560,1625,-14,0",
        "@type": "sc:Canvas",
        "label": "Google Cloud Vision API",
        "metadata": [
            {
                "label": "Text",
                "value": "宮"
            }
        ]
    },
    {
        "@id": "https://github.com/nakamura196/amami/raw/master/docs/iiif/amami/canvas/p342#xywh=1542,1674,16,37",
        "@type": "sc:Canvas",
        "label": "Google Cloud Vision API",
        "metadata": [
            {
                "label": "Text",
                "value": "骨太"
            }
        ]
    },
    {
        "@id": "https://github.com/nakamura196/amami/raw/master/docs/iiif/amami/canvas/p342#xywh=1512,1625,16,93",
        "@type": "sc:Canvas",
        "label": "Google Cloud Vision API",
        "metadata": [
            {
                "label": "Text",
                "value": "堰亮五郎"
            }
        ]
    },
    {
        "@id": "https://github.com/nakamura196/amami/raw/master/docs/iiif/amami/canvas/p342#xywh=1197,759,433,294",
        "@type": "sc:Canvas",
        "label": "Google Cloud Vision API",
        "metadata": [
            {
                "label": "Text",
                "value": "ものに、本舞派出姉人合がある。此度の角長で、あり、同經月である、奥山城照氏こそは我郡の出身者(船津村)である。記者は郡の先輩と、しては大分珍らしい方面に活躇されてみると思つて秋晴の一日同氏を訪った。主人公と云ふのはまだ三十七八位の重役イブの好紳士、刺を通すると快よく奥の八間に招ぜられて面談して下さつえ。記者の問に対して同氏は語る。「現在うちの會員は五十余名で、大渕二〇"
            }
        ]
    },
    {
        "@id": "https://github.com/nakamura196/amami/raw/master/docs/iiif/amami/canvas/p342#xywh=1326,2655,325,293",
        "@type": "sc:Canvas",
        "label": "Google Cloud Vision API",
        "metadata": [
            {
                "label": "Text",
                "value": "飛行機實習中山敏夫毎月の奄美によりまして婚里の事共或は知人の消息を知り得まして次號が待ち遠い程愛試して居りますこの感は總ての奄美出身者が同じゆうするところと存じます。宜々郷土のため御健闘の程御断り申します小生は去る月十一日少尉に任官砲術學校卒業と同時に水需校學生を命ぜられ只今水館學校の学生に起居して居ります何十二月一杯は霞ヶ浦飛行隊で飛行機質習の塚定で御座います。"
            }
        ]
    },
    {
        "@id": "https://github.com/nakamura196/amami/raw/master/docs/iiif/amami/canvas/p342#xywh=1449,3451,34,21",
        "@type": "sc:Canvas",
        "label": "Google Cloud Vision API",
        "metadata": [
            {
                "label": "Text",
                "value": "13"
            }
        ]
    },
    {
        "@id": "https://github.com/nakamura196/amami/raw/master/docs/iiif/amami/canvas/p342#xywh=1306,87,168,39",
        "@type": "sc:Canvas",
        "label": "Google Cloud Vision API",
        "metadata": [
            {
                "label": "Text",
                "value": "Magenta"
            }
        ]
    },
    {
        "@id": "https://github.com/nakamura196/amami/raw/master/docs/iiif/amami/canvas/p342#xywh=1358,3449,36,25",
        "@type": "sc:Canvas",
        "label": "Google Cloud Vision API",
        "metadata": [
            {
                "label": "Text",
                "value": "112"
            }
        ]
    },
    {
        "@id": "https://github.com/nakamura196/amami/raw/master/docs/iiif/amami/canvas/p342#xywh=1196,1105,185,278",
        "@type": "sc:Canvas",
        "label": "Google Cloud Vision API",
        "metadata": [
            {
                "label": "Text",
                "value": "三十五間位の所です。當今は寄宿否の設が出來て居をして、其處に起臥してるよすが仕事の中込が多い為め寄宿舎に在る日は殆んど稀です。縮要者側の派出婦に對する希堂は色々ありますが、白粉を無茶苦茶つける事、これが第一で仕事そつちのけで鏡と牡丹嗣毛の首引をする女を一番嫌がり"
            }
        ]
    },
    {
        "@id": "https://github.com/nakamura196/amami/raw/master/docs/iiif/amami/canvas/p342#xywh=1200,1420,263,295",
        "@type": "sc:Canvas",
        "label": "Google Cloud Vision API",
        "metadata": [
            {
                "label": "Text",
                "value": "昇直隆……小生事トルストイ誕生百年記念祭参列のため去る八月末露都へ出張の際は唐突の事とて御暇乞の餘裕もなく共磁失危仕候段不惡御容赦被下度挨以御蔭九月十三日市スクヴァ花當日より十七日まで毎日の如く記念説典にあつか、其後スクヴァ、レニングラ・ドを一通り観察の上更に此の竣斜を利用して歐洲諸國を一巡致し再びロシャを經て十月三十日無京臨朝仕候..……"
            }
        ]
    },
    {
        "@id": "https://github.com/nakamura196/amami/raw/master/docs/iiif/amami/canvas/p342#xywh=1200,2657,101,291",
        "@type": "sc:Canvas",
        "label": "Google Cloud Vision API",
        "metadata": [
            {
                "label": "Text",
                "value": "支部長重任永山宜文十月號の恋美誌で承れば、今回朝日新聞社をおやめになり、新に郷土雑誌薩隅御發行の由"
            }
        ]
    },
    {
        "@id": "https://github.com/nakamura196/amami/raw/master/docs/iiif/amami/canvas/p342#xywh=1219,723,19,13",
        "@type": "sc:Canvas",
        "label": "Google Cloud Vision API",
        "metadata": [
            {
                "label": "Text",
                "value": ".15"
            }
        ]
    },
    {
        "@id": "https://github.com/nakamura196/amami/raw/master/docs/iiif/amami/canvas/p342#xywh=1218,1959,13,12",
        "@type": "sc:Canvas",
        "label": "Google Cloud Vision API",
        "metadata": [
            {
                "label": "Text",
                "value": "17"
            }
        ]
    },
    {
        "@id": "https://github.com/nakamura196/amami/raw/master/docs/iiif/amami/canvas/p342#xywh=1149,87,83,31",
        "@type": "sc:Canvas",
        "label": "Google Cloud Vision API",
        "metadata": [
            {
                "label": "Text",
                "value": "Red"
            }
        ]
    },
    {
        "@id": "https://github.com/nakamura196/amami/raw/master/docs/iiif/amami/canvas/p342#xywh=1182,3449,40,25",
        "@type": "sc:Canvas",
        "label": "Google Cloud Vision API",
        "metadata": [
            {
                "label": "Text",
                "value": "110"
            }
        ]
    },
    {
        "@id": "https://github.com/nakamura196/amami/raw/master/docs/iiif/amami/canvas/p342#xywh=1128,3033,75,25",
        "@type": "sc:Canvas",
        "label": "Google Cloud Vision API",
        "metadata": [
            {
                "label": "Text",
                "value": "342-"
            }
        ]
    },
    {
        "@id": "https://github.com/nakamura196/amami/raw/master/docs/iiif/amami/canvas/p342#xywh=1103,3477,13,0",
        "@type": "sc:Canvas",
        "label": "Google Cloud Vision API",
        "metadata": [
            {
                "label": "Text",
                "value": "CON"
            }
        ]
    },
    {
        "@id": "https://github.com/nakamura196/amami/raw/master/docs/iiif/amami/canvas/p342#xywh=1055,1955,16,14",
        "@type": "sc:Canvas",
        "label": "Google Cloud Vision API",
        "metadata": [
            {
                "label": "Text",
                "value": "18"
            }
        ]
    },
    {
        "@id": "https://github.com/nakamura196/amami/raw/master/docs/iiif/amami/canvas/p342#xywh=995,1412,100,294",
        "@type": "sc:Canvas",
        "label": "Google Cloud Vision API",
        "metadata": [
            {
                "label": "Text",
                "value": "船の水新納恒啓一出張の車中鶴見君の英雄待望論を詠む、色氣タッブリの男也。"
            }
        ]
    },
    {
        "@id": "https://github.com/nakamura196/amami/raw/master/docs/iiif/amami/canvas/p342#xywh=1004,2140,82,127",
        "@type": "sc:Canvas",
        "label": "Google Cloud Vision API",
        "metadata": [
            {
                "label": "Text",
                "value": "御大典齒拜觀記"
            }
        ]
    },
    {
        "@id": "https://github.com/nakamura196/amami/raw/master/docs/iiif/amami/canvas/p342#xywh=1005,3453,24,21",
        "@type": "sc:Canvas",
        "label": "Google Cloud Vision API",
        "metadata": [
            {
                "label": "Text",
                "value": "18"
            }
        ]
    },
    {
        "@id": "https://github.com/nakamura196/amami/raw/master/docs/iiif/amami/canvas/p342#xywh=934,87,124,33",
        "@type": "sc:Canvas",
        "label": "Google Cloud Vision API",
        "metadata": [
            {
                "label": "Text",
                "value": "Yellow"
            }
        ]
    },
    {
        "@id": "https://github.com/nakamura196/amami/raw/master/docs/iiif/amami/canvas/p342#xywh=855,1084,243,289",
        "@type": "sc:Canvas",
        "label": "Google Cloud Vision API",
        "metadata": [
            {
                "label": "Text",
                "value": "在の仕事が有望なるを知つて、之が經營をなすに至つたものであると。家庭には花子夫人との間に長男欣一君(七才)次男增男君(五才)の二令忍がある。因に郡出身の方々へは特別の利便を図るとの事である、住所及電話番號は左記の通り。東京市本鄉网湯出三組町八叫番地本州派出始人命電話下谷七、二三四番"
            }
        ]
    },
    {
        "@id": "https://github.com/nakamura196/amami/raw/master/docs/iiif/amami/canvas/p342#xywh=970,1484,11,0",
        "@type": "sc:Canvas",
        "label": "Google Cloud Vision API",
        "metadata": [
            {
                "label": "Text",
                "value": "X"
            }
        ]
    },
    {
        "@id": "https://github.com/nakamura196/amami/raw/master/docs/iiif/amami/canvas/p342#xywh=953,2156,36,38",
        "@type": "sc:Canvas",
        "label": "Google Cloud Vision API",
        "metadata": [
            {
                "label": "Text",
                "value": "神戶特師"
            }
        ]
    },
    {
        "@id": "https://github.com/nakamura196/amami/raw/master/docs/iiif/amami/canvas/p342#xywh=961,2226,20,52",
        "@type": "sc:Canvas",
        "label": "Google Cloud Vision API",
        "metadata": [
            {
                "label": "Text",
                "value": "中村真一"
            }
        ]
    },
    {
        "@id": "https://github.com/nakamura196/amami/raw/master/docs/iiif/amami/canvas/p342#xywh=957,3411,14,3",
        "@type": "sc:Canvas",
        "label": "Google Cloud Vision API",
        "metadata": [
            {
                "label": "Text",
                "value": "3"
            }
        ]
    },
    {
        "@id": "https://github.com/nakamura196/amami/raw/master/docs/iiif/amami/canvas/p342#xywh=360,-2,790,125",
        "@type": "sc:Canvas",
        "label": "Google Cloud Vision API",
        "metadata": [
            {
                "label": "Text",
                "value": "KodakColorControlPatchesCyanBlue"
            }
        ]
    },
    {
        "@id": "https://github.com/nakamura196/amami/raw/master/docs/iiif/amami/canvas/p342#xywh=735,87,107,32",
        "@type": "sc:Canvas",
        "label": "Google Cloud Vision API",
        "metadata": [
            {
                "label": "Text",
                "value": "Green"
            }
        ]
    },
    {
        "@id": "https://github.com/nakamura196/amami/raw/master/docs/iiif/amami/canvas/p342#xywh=745,1105,20,200",
        "@type": "sc:Canvas",
        "label": "Google Cloud Vision API",
        "metadata": [
            {
                "label": "Text",
                "value": "スポーツマンシップの化"
            }
        ]
    },
    {
        "@id": "https://github.com/nakamura196/amami/raw/master/docs/iiif/amami/canvas/p342#xywh=766,3456,-11,0",
        "@type": "sc:Canvas",
        "label": "Google Cloud Vision API",
        "metadata": [
            {
                "label": "Text",
                "value": "IQ"
            }
        ]
    },
    {
        "@id": "https://github.com/nakamura196/amami/raw/master/docs/iiif/amami/canvas/p342#xywh=367,754,733,297",
        "@type": "sc:Canvas",
        "label": "Google Cloud Vision API",
        "metadata": [
            {
                "label": "Text",
                "value": "ます。次が勤務中の交代で自分獨りの都合から仲間の女と交代する、また夜退くなつてから外出したがる女も極端に嫌はれます。派出婦を中心として情事沙汰が度々問題となる様ですが、それは双方共考へねばならぬ事です。私は之を防ぎ、日派用姉が理想的の家政婦となる島めには派出姉専門の學校を設けては必要な教育を施し、産婆や看護婦の様に一定の免許状を與へる様にしたら非常に好成績だらうと思つて、其の貨現に苦心しておす。當の合員は至つて真面目に働きますので各方面から非常な資試を受けてみます。御淡様で商革繁昌と云つた風で、これも採用する時、良質の婦人を嚴選の上入會させてめる結果です。」とかゆい所に手のとどく程詳細に話された。同氏が現在の成功をかち得る迄には共施には幾多の涙ぐましい話がある。質に氏は獨典獨行不断の努力が今日酬いられたのである明治三十九年十六才の時單身上京或時は泉二博士の書生となり、或は星野博士の助手となり、或は貯金局に勤め途に奥山貴族院議員の2かる所となり、同邸の書生をしつ.早格田賞校に学び、の功成つて、大正二年三月同校を卒業と同時に十五銀行に勤務する事質に十数年空\"十二月同行を退して現"
            }
        ]
    },
    {
        "@id": "https://github.com/nakamura196/amami/raw/master/docs/iiif/amami/canvas/p342#xywh=370,2317,729,304",
        "@type": "sc:Canvas",
        "label": "Google Cloud Vision API",
        "metadata": [
            {
                "label": "Text",
                "value": "内限で拝し奉る光発を得ずば退いて病人と共に心眼を以つて遙拝し奉る積りで先づ妻と長女芳子(二)と看護婦一人に叔母を御供させて弟の角帽を案内役として元日入洛せしめた。五人のお上りさん選は五日市內見物明六日叡山登山のブログラムだから小生に來られないかと京都の旅館から五日の晩電話がかつて來たが五日までの所重い病人が歌人ねて出られ相でなかつたが六日の午后の往診の重症の人々は中し合はた様に急に快方に向つたのでこれ幸と往診修了后早速阪急から新京阪に乘り御大典の都に潜いたのは然たるイルミネーションに照り焼いてみる頃であった小生の京都に對する従来の印象は微の生えた古ぼけた汚い町で時勢に取り残された「生ける屍」であつたが御大典を一製轍期として流石は日本の誇都だという壮厳な印象に一變して仕舞つつた。タクシィはなく吉岡旅館の南に横付けにされたっ先後の人の神上りさん達は丁度、食中でよろ山海の珍味は所せき食でに雑然とならべられてある。一我校見なかつた芳子は球団ざる場所で換期せざる父が陥って来たので喜びに超えの如く嬉々としてはウチャン沖りといふ。次いですの合うのは、モンキ!ねえ」といどうして」と聞く「姉ちゃんあーんあiん。かあちやんないない」といつて泣く真似"
            }
        ]
    },
    {
        "@id": "https://github.com/nakamura196/amami/raw/master/docs/iiif/amami/canvas/p342#xywh=371,1413,588,297",
        "@type": "sc:Canvas",
        "label": "Google Cloud Vision API",
        "metadata": [
            {
                "label": "Text",
                "value": "昭和三年十月三十日午前九時日本郵船株式分社注文北米航路優秀船「淺丸」見事に選水仕咲淺間の由日本郵船株式會社の新造巨船三船の内第一船は岡→大宮町銀座官幣大忙淺間神社の祠號をとつて送間(あさみ)丸と命名せられたのであるが、世人は芝田(あさ)といへば直ちに信州の噴火山淺間山を連想し、常士山麓の此の神社を後間(せんげん)と背試し一居るけれども、此の御乱の正し4柄へ方は淺間(あさま)神述であつて淺間(せんげん)ではない。浅間抑肝、祭神は大山祇神の女にして皇孫瓊々杵尊の后たる木花咲耶姫命に在すことは衆知のところ、古の駿河國一宮で、往古は社殿なく富士山を道に御神醒として仰いで居たが、垂仁天皇の三年八月、地を山宮(大宮の北一里中)に相して始めて社設の建設成つた小城天皇の大同元年、坂上田村感に勅して現在の地に神殿を営み、山宮からこいに奉還せられた。前後今に造ぶ千百除年山宮以來質に"
            }
        ]
    },
    {
        "@id": "https://github.com/nakamura196/amami/raw/master/docs/iiif/amami/canvas/p342#xywh=695,1120,29,207",
        "@type": "sc:Canvas",
        "label": "Google Cloud Vision API",
        "metadata": [
            {
                "label": "Text",
                "value": "森山早大應援團長"
            }
        ]
    },
    {
        "@id": "https://github.com/nakamura196/amami/raw/master/docs/iiif/amami/canvas/p342#xywh=397,2647,707,317",
        "@type": "sc:Canvas",
        "label": "Google Cloud Vision API",
        "metadata": [
            {
                "label": "Text",
                "value": "御發展のほど誠にお芽出度御座います、早速御喜び申上げなければなりませんが私も相題忙がしい生活を統けてみるので失履いたしした。社會民衆磁豊島支部も漸次發展し、十ヶ町に分會が出來まして、今では城北一帶に政治的一大勢力を結成しつつあります。その聯絡統制のため夜分は殆んど家に居たことはありせん。本月2日高田町鬼子母神境內高會舘で本年度の支部大便を開き、盛會裡に二十余の議案を審議し可決または否決いたしました。無産織一支部の大食としては未曾有だといはれてみます。役員の任期は一ヶ年でありますが、本大會で私が支部長を重任することになりました。北上に先般新に賀川豊彦氏等の主唱に依り結成されました全國非戦同服の執行委員教育部長を引受けましたので、何一忙がしくなることと思つてわす。既成政に近づきになれば、何かの御裾分けに預かることもありせうが、無産階級の解放運動では自分の持てるものでも失ふのであります。然し大なる社會改造延動の!部を病任してあると思ふだけで肉躍り血湧くのであります。薩隅お送り下さるものと待つてみましたが、申込まなかつたためか送ってきませんがお送り下さい、お願いいたします。"
            }
        ]
    },
    {
        "@id": "https://github.com/nakamura196/amami/raw/master/docs/iiif/amami/canvas/p342#xywh=368,1995,559,295",
        "@type": "sc:Canvas",
        "label": "Google Cloud Vision API",
        "metadata": [
            {
                "label": "Text",
                "value": "知里の叔父宮死后全く一人ボッチで哀愁に幕れてみた叔母の氣時しにもと京阪神見物や湯治をすくめてみたが幸御大典奉拝を兼ねユルユル見物に來られたので京都帝大の弟に旅館を交渉せしめた所三條小橋の吉岡旅館に五日から八日までの謀約で一金が借りられた御大典に際しては両陛下を始め泰り各宮樣及び各開條全部並に奉拜の赤子が日本全國の津々浦々或は外國からも無數に入浴の事なれば旅館を得るは容易な事ではないがわざわざ南端の孤島から拝観に来られた叔母が他界の叔父に土陸話とするに越しからぬ旅館(来宮樣が御消りになつた)を借り得た事は弟の角輪の御険だと角潮に敬の意を表しておく峨古の御大典であるから八千萬の民草は誰一人として拝観し恭り度くない者のあらう筈がない。唯然し小生は厳柄歴下の赤子の生命を孤かつてのる園係上満人を放つといて陸下を奉拝した所で封つて陸下の大御心にそひる所以でないと思ってるから身直接京都に行"
            }
        ]
    },
    {
        "@id": "https://github.com/nakamura196/amami/raw/master/docs/iiif/amami/canvas/p342#xywh=369,1085,308,295",
        "@type": "sc:Canvas",
        "label": "Google Cloud Vision API",
        "metadata": [
            {
                "label": "Text",
                "value": "……第一回明治節の口たる十一月三日東京市外上井草で行はれた同志社大學對明治大學の野校陸上競技で少数の同志乱に混つて,早稲田大學應援團長森田範秀君外十敗名の幹部が盛んに同志社側を軽授してみた。これは先日、淀川の京都帝大、早袴田大學競艇の際、早大應援團が同志族援團の熱烈な盛授を受けた。所が十四艇身の大差で早大優勝し、全國の潮を揺るに至ったが早大は同志社のこの技に感じ、いつか神巡返しをと思つて居た矢先だったので、常口の早法写球戦をも犠牲にして一肌脱いで来たのである"
            }
        ]
    },
    {
        "@id": "https://github.com/nakamura196/amami/raw/master/docs/iiif/amami/canvas/p342#xywh=577,3467,14,3",
        "@type": "sc:Canvas",
        "label": "Google Cloud Vision API",
        "metadata": [
            {
                "label": "Text",
                "value": "3"
            }
        ]
    },
    {
        "@id": "https://github.com/nakamura196/amami/raw/master/docs/iiif/amami/canvas/p342#xywh=345,3405,46,19",
        "@type": "sc:Canvas",
        "label": "Google Cloud Vision API",
        "metadata": [
            {
                "label": "Text",
                "value": "inches"
            }
        ]
    },
    {
        "@id": "https://github.com/nakamura196/amami/raw/master/docs/iiif/amami/canvas/p342#xywh=345,3445,13,14",
        "@type": "sc:Canvas",
        "label": "Google Cloud Vision API",
        "metadata": [
            {
                "label": "Text",
                "value": "cm"
            }
        ]
    },
    {
        "@id": "https://github.com/nakamura196/amami/raw/master/docs/iiif/amami/canvas/p342#xywh=215,1477,23,163",
        "@type": "sc:Canvas",
        "label": "Google Cloud Vision API",
        "metadata": [
            {
                "label": "Text",
                "value": "鄉土近事"
            }
        ]
    },
    {
        "@id": "https://github.com/nakamura196/amami/raw/master/docs/iiif/amami/canvas/p342#xywh=220,2669,10,151",
        "@type": "sc:Canvas",
        "label": "Google Cloud Vision API",
        "metadata": [
            {
                "label": "Text",
                "value": "まない次第であります。"
            }
        ]
    },
    {
        "@id": "https://github.com/nakamura196/amami/raw/master/docs/iiif/amami/canvas/p342#xywh=-1,722,257,326",
        "@type": "sc:Canvas",
        "label": "Google Cloud Vision API",
        "metadata": [
            {
                "label": "Text",
                "value": "をする。何の事かからん。たでも動物医物に行ったら送子があてはちやんがないといよて泣いてんたらが其の子の持つてある御菓子をオリから手を出してそつた。母の説明を聞いて(迷子のエピソードが解かると同時に、一寸の虫にも五分の魂、充分に發表は出来ないながらそれだけのビルドを購表に描き然かも「モンキー馬鹿ね」といふ結論まで抽出するに至つては自分の子供ながら感心せざるを得ない。自分の子供に感心したり御馳走の多いのに感心したりしてみると「即阪"
            }
        ]
    },
    {
        "@id": "https://github.com/nakamura196/amami/raw/master/docs/iiif/amami/canvas/p342#xywh=14,1065,237,320",
        "@type": "sc:Canvas",
        "label": "Google Cloud Vision API",
        "metadata": [
            {
                "label": "Text",
                "value": "れにきながらパノラの週末有の美姿をこらせる全京都が車窓に展開する。街を通る人々の流れは、拉武の昔より京都に育ち、黄茂川の水で路上げた上人の肌に、現代スポーツの産物なる健康美を、三越大丸高島屋の意匠をこらした衣袋で包んだ様な美形が不夜城の電光に其美を擁してある約三十分も走った頃明日の医療御逝為の道筋烏丸通に出る。時に午后八時。京都驛から御所まで約堂里複線の電車道の南傾に疾走車道徐行車道、街路樹歩道その兩側が店舗といふの如きコンクリーの都大路(十五間)の中央の電車道"
            }
        ]
    },
    {
        "@id": "https://github.com/nakamura196/amami/raw/master/docs/iiif/amami/canvas/p342#xywh=128,2667,75,294",
        "@type": "sc:Canvas",
        "label": "Google Cloud Vision API",
        "metadata": [
            {
                "label": "Text",
                "value": "節婚孝子表彰御大テンに際し大島支墜社會課では郡内の幸子姉を選び支薩長より表彰状と金品の授與を為した。"
            }
        ]
    },
    {
        "@id": "https://github.com/nakamura196/amami/raw/master/docs/iiif/amami/canvas/p342#xywh=-1,1996,239,310",
        "@type": "sc:Canvas",
        "label": "Google Cloud Vision API",
        "metadata": [
            {
                "label": "Text",
                "value": "現今午前一時まで六時間の国努力しつじけたのである。其の間可なり南が降ったらしい。弟の環定では明朝六時まで一人で四人分の席を不眠不休で固守し小生等を旅館に安眠させ然して后小生等を迎へに來る積りだつたがそんな虫のよい事は情況が許さいので不二夫を呼んで斜させ早速迎へに來たのである。小生等が着席した頃は既にから御所まで一里餘十五間道路の兩側は(御通過の餘地をあし)立錐の除もない人間のスシヅメである。営局の豫定で四十万の席を取りたるも確かな筋の計みてる"
            }
        ]
    },
    {
        "@id": "https://github.com/nakamura196/amami/raw/master/docs/iiif/amami/canvas/p342#xywh=10,1415,178,296",
        "@type": "sc:Canvas",
        "label": "Google Cloud Vision API",
        "metadata": [
            {
                "label": "Text",
                "value": "賜饌功労者十一月十六日七高における本縣地方思ぐに召された功労者は三百六十六名あつたかその内本郡からは左記諸氏豊島|楽丸田狭義」森百太郎」宮原清二乾添田重信熊富田貞次郎茂久親秋"
            }
        ]
    },
    {
        "@id": "https://github.com/nakamura196/amami/raw/master/docs/iiif/amami/canvas/p342#xywh=6,2324,229,321",
        "@type": "sc:Canvas",
        "label": "Google Cloud Vision API",
        "metadata": [
            {
                "label": "Text",
                "value": "なけれどわれたコンクリの冷気はコモを通し毛布を通し料部に答える。各々の最ざるが如く管団の考官五千は音ゆる方面に其の堂々たる眼光を放ち絶えずサイドカー付のオートバィ柔りの警官も通る。タクシィは絶えず左し右して無限の拝観希望者を有限の場所に転送すれば割り込むべき原な含め又乘り來たるタクシーで踊る始末、其中に五時になつて夜が明けると共に電車は更らに無限の人々を送込めど殆んど全部空しく謝らざるを得ざるは気の毒なれど昨晚行の口より雷雨を物とも"
            }
        ]
    },
    {
        "@id": "https://github.com/nakamura196/amami/raw/master/docs/iiif/amami/canvas/p342#xywh=105,2750,11,2",
        "@type": "sc:Canvas",
        "label": "Google Cloud Vision API",
        "metadata": [
            {
                "label": "Text",
                "value": "節"
            }
        ]
    },
    {
        "@id": "https://github.com/nakamura196/amami/raw/master/docs/iiif/amami/canvas/p342#xywh=103,2782,12,2",
        "@type": "sc:Canvas",
        "label": "Google Cloud Vision API",
        "metadata": [
            {
                "label": "Text",
                "value": "婦"
            }
        ]
    },
    {
        "@id": "https://github.com/nakamura196/amami/raw/master/docs/iiif/amami/canvas/p342#xywh=1,2802,89,178",
        "@type": "sc:Canvas",
        "label": "Google Cloud Vision API",
        "metadata": [
            {
                "label": "Text",
                "value": "與論村麥屋伊東ウシ(四八)伊仙村系木名糸ウ(四七)"
            }
        ]
    }
]