[
    {
        "@id": "https://github.com/nakamura196/amami/raw/master/docs/iiif/amami/canvas/p309#xywh=2337,671,56,311",
        "@type": "sc:Canvas",
        "label": "Google Cloud Vision API",
        "metadata": [
            {
                "label": "Text",
                "value": "品杯民自身の自発起によらねばならぬことた々も言ふておいた。"
            }
        ]
    },
    {
        "@id": "https://github.com/nakamura196/amami/raw/master/docs/iiif/amami/canvas/p309#xywh=2291,720,28,135",
        "@type": "sc:Canvas",
        "label": "Google Cloud Vision API",
        "metadata": [
            {
                "label": "Text",
                "value": "よく働けば"
            }
        ]
    },
    {
        "@id": "https://github.com/nakamura196/amami/raw/master/docs/iiif/amami/canvas/p309#xywh=2105,716,174,301",
        "@type": "sc:Canvas",
        "label": "Google Cloud Vision API",
        "metadata": [
            {
                "label": "Text",
                "value": "点されない」でもない第一師範學校長場今朝治校長は出数ん日名刺日に開催され人の校長合にはみ、翌日古仁屋に出ま更に2回に渡って1ヶ村各所においてねん日な味強法を授け十八日に公教育方面においては大に続してある。サー谷村のぶえにゃはしてないもある?"
            }
        ]
    },
    {
        "@id": "https://github.com/nakamura196/amami/raw/master/docs/iiif/amami/canvas/p309#xywh=2100,1032,301,324",
        "@type": "sc:Canvas",
        "label": "Google Cloud Vision API",
        "metadata": [
            {
                "label": "Text",
                "value": "的い用授を開ることは城も必要なことであらうと考えた。八德之島は大島本品に比し耕地も多いのであろから、良倒さへすれば砂価やの生産と和ち決して続的に恵まれない心でもないやうに思ふ、即ち交通機郎その世の整備を見つ品民にしてみりするあらば發展の見込み充分である。<大島の民話に同点のことを一次世の島」と以つたものであるが各際島の日には原様な感っあらうが。しかしそれは決して全部ではない大島の地形からしれば能力に頼らねば号に定ちいたらあらうが、にどっとはがーく考えてはならない。"
            }
        ]
    },
    {
        "@id": "https://github.com/nakamura196/amami/raw/master/docs/iiif/amami/canvas/p309#xywh=2105,1388,278,315",
        "@type": "sc:Canvas",
        "label": "Google Cloud Vision API",
        "metadata": [
            {
                "label": "Text",
                "value": "て以来多方面に活動され、當地にも昨年末見えられ、日本内地にも東京、大阪、名古屋方と妙回往復され、その外天津方面から洲方面と旅行をなし、大連に於ける各方面ともだん、連絡が取れ、事業も日一日と確實性を帯びて来て居ります。最早漢口に戻る必要もなく二万数千間をかけて彼地に新築した家り店分し,將來大速に確固たる地盤を築くべく努力中であります。何桃兄は稀に見るの人格家でありますから初対面の人でも直にその容にしては引き着けらると云ム德をかな味で来必手た成本をされる事として活ります、も言"
            }
        ]
    },
    {
        "@id": "https://github.com/nakamura196/amami/raw/master/docs/iiif/amami/canvas/p309#xywh=2095,2000,306,1023",
        "@type": "sc:Canvas",
        "label": "Google Cloud Vision API",
        "metadata": [
            {
                "label": "Text",
                "value": "教員は正教員の数割合に少いか判らんが、る、母校長會では白人の校長達が熱烈なる意感想を申して見ると真面目に落付いて仕事に降念ない様だ又児童見を致心に真剣に發表し、緊張し切つたもの一、與論の一致点を獲見する事(例へは交通の入學及出席歩合も食い、設備は內地のよい問題の場合甲論乙較議論百出て在るが夫れをだ。學校に比ぶるとよくないが亀津小學校の如き統一握探して同一歩調を取りて與論に訴へ(これは昨年同島に上味下の行幸を仰いで局に迫ること)如断する為めには郡内郡外に校公も相官ないのである、今度の旅行は船り聖恩の窮に感激したことに原因しようと思機関を設くる必要あらん御考慮を願ひます。都合により夜半出発したこともあり、亦一口ふが一面飲島幹規典が極めて質な無成な指何回ら講演をし非常な院わたしい旅行で紙上を通じて訴へたいに努めてみるのも一効果の現はれでなくてあつた、今些し指導の方法を講じて彼等の智はならない、聞けば各學校各學殺とも學校支長崎堂大破常重識然に副ムや5努力する必要を感感すられに學校経営案を編んてる今度の論文を見……日を追い月を重ねるにつれて登々內容豊た。ても、理論の研究も相あり、周園や手工、當に各方面に活動して來た我が可愛い唯一無作法、友建方面へ特月に立派な指系統案をこの土社「奄美における貴殿の御活躍を學習態度の作ってる、是は大島郡教育界の良い現はれ先づ以て配備申し上げ培土を巻く際れ居るて置に驚かされたを提る一つだと思う、く若い時と午教育首に重りていいか喜びを実へもおられる子大生できうか、時とは違みたきりあさりはいきいき交せましては、身にてちこにいる人よ~"
            }
        ]
    },
    {
        "@id": "https://github.com/nakamura196/amami/raw/master/docs/iiif/amami/canvas/p309#xywh=2106,2855,9,108",
        "@type": "sc:Canvas",
        "label": "Google Cloud Vision API",
        "metadata": [
            {
                "label": "Text",
                "value": "Cランクとより"
            }
        ]
    },
    {
        "@id": "https://github.com/nakamura196/amami/raw/master/docs/iiif/amami/canvas/p309#xywh=2099,723,11,298",
        "@type": "sc:Canvas",
        "label": "Google Cloud Vision API",
        "metadata": [
            {
                "label": "Text",
                "value": "だが、というりん気に"
            }
        ]
    },
    {
        "@id": "https://github.com/nakamura196/amami/raw/master/docs/iiif/amami/canvas/p309#xywh=2098,1420,13,282",
        "@type": "sc:Canvas",
        "label": "Google Cloud Vision API",
        "metadata": [
            {
                "label": "Text",
                "value": "なにより高品によっても気に"
            }
        ]
    },
    {
        "@id": "https://github.com/nakamura196/amami/raw/master/docs/iiif/amami/canvas/p309#xywh=2092,1065,9,218",
        "@type": "sc:Canvas",
        "label": "Google Cloud Vision API",
        "metadata": [
            {
                "label": "Text",
                "value": "パラノーラインっ!"
            }
        ]
    },
    {
        "@id": "https://github.com/nakamura196/amami/raw/master/docs/iiif/amami/canvas/p309#xywh=1935,84,112,33",
        "@type": "sc:Canvas",
        "label": "Google Cloud Vision API",
        "metadata": [
            {
                "label": "Text",
                "value": "Black"
            }
        ]
    },
    {
        "@id": "https://github.com/nakamura196/amami/raw/master/docs/iiif/amami/canvas/p309#xywh=1802,43,254,23",
        "@type": "sc:Canvas",
        "label": "Google Cloud Vision API",
        "metadata": [
            {
                "label": "Text",
                "value": "©Kodak,2007TM:Kodak"
            }
        ]
    },
    {
        "@id": "https://github.com/nakamura196/amami/raw/master/docs/iiif/amami/canvas/p309#xywh=1909,2486,17,116",
        "@type": "sc:Canvas",
        "label": "Google Cloud Vision API",
        "metadata": [
            {
                "label": "Text",
                "value": "吉高碧水"
            }
        ]
    },
    {
        "@id": "https://github.com/nakamura196/amami/raw/master/docs/iiif/amami/canvas/p309#xywh=1814,1088,186,294",
        "@type": "sc:Canvas",
        "label": "Google Cloud Vision API",
        "metadata": [
            {
                "label": "Text",
                "value": "れば全く島民の努力が足りないと云つてよからう、毒蛇ハブが出没するので危険なために放任されてるであらうかもしれぬが、之とて今の様な鮮蹴にして置くからハブも棲息するのである、耕地にすれば幾分減し樣し込出ても見付け易からうから危険も減することと思ふ。"
            }
        ]
    },
    {
        "@id": "https://github.com/nakamura196/amami/raw/master/docs/iiif/amami/canvas/p309#xywh=1761,1417,238,295",
        "@type": "sc:Canvas",
        "label": "Google Cloud Vision API",
        "metadata": [
            {
                "label": "Text",
                "value": "れます、……何か紙上を通じて郡當局又は先造有志と思想の聯絡乃至は意見の交換なしたく兼ね、念する處では御座居ますが暇ある様で暇のないのが科の學生でいつも授會を取逃して居り非、之からは暇を利用して何か小さな胸底にろく燃え上る思念の一端を先諸兄に訴へて見たいと思ひます、而して御指導を仰ぎ度いと念じて居り升何卒宣敷おブひ申します。"
            }
        ]
    },
    {
        "@id": "https://github.com/nakamura196/amami/raw/master/docs/iiif/amami/canvas/p309#xywh=1869,2386,-14,0",
        "@type": "sc:Canvas",
        "label": "Google Cloud Vision API",
        "metadata": [
            {
                "label": "Text",
                "value": "(i)"
            }
        ]
    },
    {
        "@id": "https://github.com/nakamura196/amami/raw/master/docs/iiif/amami/canvas/p309#xywh=1590,756,412,294",
        "@type": "sc:Canvas",
        "label": "Google Cloud Vision API",
        "metadata": [
            {
                "label": "Text",
                "value": "を見せてみた、かく熱心に懸賞論文に応募して居る如きは到底內地でも多くは見られない現象である。遺跡から大島郡が進み動く今後の進動が大知されるのであった、何分二百五海里の彼方に離作せる交通不便な大島で三日間の校長會に出るに往復二週間を要するところもある位であるから河に氣のな次第である、が將來出来るだけ內地の教育界と企々接觸を保ち、現時の状勢で進んだなら所謂大島郡を、教育の方からでも救ひうると思ふ、又大島中學校も龍野校長就任以来、內容設備着々刷新され良成績を奉げつあるが、同校出身の我校二部生に見ても端かしい教育効果を偲ばずに居れない。"
            }
        ]
    },
    {
        "@id": "https://github.com/nakamura196/amami/raw/master/docs/iiif/amami/canvas/p309#xywh=1804,1162,-10,0",
        "@type": "sc:Canvas",
        "label": "Google Cloud Vision API",
        "metadata": [
            {
                "label": "Text",
                "value": "×"
            }
        ]
    },
    {
        "@id": "https://github.com/nakamura196/amami/raw/master/docs/iiif/amami/canvas/p309#xywh=1721,84,142,33",
        "@type": "sc:Canvas",
        "label": "Google Cloud Vision API",
        "metadata": [
            {
                "label": "Text",
                "value": "3/Color"
            }
        ]
    },
    {
        "@id": "https://github.com/nakamura196/amami/raw/master/docs/iiif/amami/canvas/p309#xywh=1716,1473,18,167",
        "@type": "sc:Canvas",
        "label": "Google Cloud Vision API",
        "metadata": [
            {
                "label": "Text",
                "value": "理想的の郷土雑誌たれ"
            }
        ]
    },
    {
        "@id": "https://github.com/nakamura196/amami/raw/master/docs/iiif/amami/canvas/p309#xywh=1588,1088,190,292",
        "@type": "sc:Canvas",
        "label": "Google Cloud Vision API",
        "metadata": [
            {
                "label": "Text",
                "value": "大島振興には島民の精,的大を肝要とすると思ふ、各離島を經て沖繩縣に行ったがモゥ五十日雨が降り祝いてあるのでジメントして氣持の悪さつたらなかつた、此處は二年前から産業助成を貰つてゐるそうで大分引締つてある様に思はれた、耕地もよく利用されて甘底世論が繁茂してみた。"
            }
        ]
    },
    {
        "@id": "https://github.com/nakamura196/amami/raw/master/docs/iiif/amami/canvas/p309#xywh=1677,1618,15,19",
        "@type": "sc:Canvas",
        "label": "Google Cloud Vision API",
        "metadata": [
            {
                "label": "Text",
                "value": "弘明"
            }
        ]
    },
    {
        "@id": "https://github.com/nakamura196/amami/raw/master/docs/iiif/amami/canvas/p309#xywh=1534,83,113,35",
        "@type": "sc:Canvas",
        "label": "Google Cloud Vision API",
        "metadata": [
            {
                "label": "Text",
                "value": "White"
            }
        ]
    },
    {
        "@id": "https://github.com/nakamura196/amami/raw/master/docs/iiif/amami/canvas/p309#xywh=1284,2000,712,296",
        "@type": "sc:Canvas",
        "label": "Google Cloud Vision API",
        "metadata": [
            {
                "label": "Text",
                "value": "も之を保護する防風林あつて好成績も､げ得られる。公の風は横ナグリに吹くと見えて、當局の試験によると樹の高さの四倍の長さの絶望しか防風効力がないそうである、山林に出來た樹木は燃料とし或は用材として沖縄へ出せばょい沖縄は今のところ當分自給月足は思ひよらぬことの様であつた、現在でも年々三十萬回位の用材燃料は移入されてある、大島は質がよくて雨量が多く、空中の氣も多く、氣候温暖で樹木の成長には過べて良い條作を備へてみる、それでも樹木の休止期と云ふものがなく成長するそして材質も堅いのが用来てみる、只その林業を妨げるものにハゲがかる、が恐さに山に出かけるのもツィおつくになるし,山や野良に出ても夕方も早く引上げてると云ふことになるのであらう。《大島の住民は決して函民ではない、ハブのために止なく歯民に等しい程度になつているものと思ふ、事賀ハブの状息りない永良部等は相當に林菜もしてある、大島の此の窮狀を救みには、トゥしても産業助成を得ねばならぬ極端な形容をするならこでも日本の領土內かと思はれる位に悲惨なものである、大島經濟の産業助成の實現のためには郡民は固より.縣民一般が努力されねばならぬと思"
            }
        ]
    },
    {
        "@id": "https://github.com/nakamura196/amami/raw/master/docs/iiif/amami/canvas/p309#xywh=1366,2326,464,296",
        "@type": "sc:Canvas",
        "label": "Google Cloud Vision API",
        "metadata": [
            {
                "label": "Text",
                "value": "私用を審び卯月の下旬に台湾をたつて東京に行き所用を終へて今原兄迄來てをる。福澤瑞明、小林三郎、笠島孝作、仲山元,花城永夢、大岡死後、木村撃,西元五郎、竹林保太郎、純所純忠、冷却装題、中林道後、指宿良英の諸兄と合つて非常に愉快でした。凡そ友人に固有的な人と一時的な人の二様がある。同婦人たると否とを問はず前者は腹の底をつた所謂信友であって後者は職務上その他の社的生活關係で交誼を結ぶもので當該係が斷絕すれば多くの場合他人となる価類の友達である。一年一回の年賀状すら出さめ知人でも十年なり二十年を經て警つでも昔の愛情が少しも薄らいでない朋友が多かつた。人情紙よりもうすい世の中に、人間味の源厚な朋無を見出すときに、非常なる快感を起すのであ"
            }
        ]
    },
    {
        "@id": "https://github.com/nakamura196/amami/raw/master/docs/iiif/amami/canvas/p309#xywh=1255,2653,739,297",
        "@type": "sc:Canvas",
        "label": "Google Cloud Vision API",
        "metadata": [
            {
                "label": "Text",
                "value": "べく其前に於て決議相成りたる日、同年十一月内務部長より通牒と同時に書類不備の康明変を以て返戻相成、夫々整理の上更に十二月廿六日再提出し、越へて昭和三年一月十四日認可促進方を重ねて景講し置きしに依り、遅くも年度内には何分指令に接するものと期待し居りしに、二年度經過後に至るも督として何等の消息なく不審に堪へさるにより、非公式に縣に問い合せしに、請書は不備の個所等を施し速かに提出すべく當時返戻の磁干今再提出なく、然るに政府に於ては年度經過後の今日迄書類提出無之は希望なきものと認め右融通方の通知は之を取消す旨通牒あり共日本年四月二十五日付を以て支臨經由做達し置きたりとの事なり、於茲か當町は內務部長這次の御視察の援台に此の事實を指摘して陳情し置をたる次第に有之,然るに支施長は共の後本月七日に至り入兵批條例設定許可票講と共に、當初哲類提出より六ヶ月後の今頃に至りて不秘密とか縣産に於ても不許可の意なりとか茶屋附會の理由を附して返戻し越せり、この支感の主張は何等根城なく固より取るに足らざるなり、若し假りに支店の主張を適當なりとせんか、上級臨なるいは何を苦んで叙上の如き文書の往復手數の煩雑を取てするの要がある、又現に縣営局に於ても入貨稅は何ほ研究の餘地ありと云ひ、名瀬町亦"
            }
        ]
    },
    {
        "@id": "https://github.com/nakamura196/amami/raw/master/docs/iiif/amami/canvas/p309#xywh=1536,1128,32,170",
        "@type": "sc:Canvas",
        "label": "Google Cloud Vision API",
        "metadata": [
            {
                "label": "Text",
                "value": "何より林業第一"
            }
        ]
    },
    {
        "@id": "https://github.com/nakamura196/amami/raw/master/docs/iiif/amami/canvas/p309#xywh=1459,3455,29,21",
        "@type": "sc:Canvas",
        "label": "Google Cloud Vision API",
        "metadata": [
            {
                "label": "Text",
                "value": "13"
            }
        ]
    },
    {
        "@id": "https://github.com/nakamura196/amami/raw/master/docs/iiif/amami/canvas/p309#xywh=1259,1417,392,297",
        "@type": "sc:Canvas",
        "label": "Google Cloud Vision API",
        "metadata": [
            {
                "label": "Text",
                "value": "なつかしい「奄美」の二字、私は飛び上りました。郷土雑誌にふさわしいその表紙、そして完全に近いその內容の充實さ。美事さ。郷土文藝、消息、各地奄美會情報など止めてはなりません。又卷頭の大島選舉の結果,迷撃の結果報告、郡人出世物語、練習艦秋迎歌なども大へんよいと思ひました。……奄美社のモットーである「鄰土色の豊かさ」を實現せしむるやに、郡内の風景寫眞又は槍画、い。。。。。。。。。。。。。。。。。。。。。。。。。。。郷土の時事、島の陣説、島の地理、歴史、。。。。。。。。。術その他學術的研究を多く取って、成るべく誌上で口論をするやうな不心得なり意見は餘採らないやうにして、そして吾が郷土雑誌「奄美」の理想的な痛土誌となるやうに努力してほしいのであります。"
            }
        ]
    },
    {
        "@id": "https://github.com/nakamura196/amami/raw/master/docs/iiif/amami/canvas/p309#xywh=1320,83,144,39",
        "@type": "sc:Canvas",
        "label": "Google Cloud Vision API",
        "metadata": [
            {
                "label": "Text",
                "value": "Magenta"
            }
        ]
    },
    {
        "@id": "https://github.com/nakamura196/amami/raw/master/docs/iiif/amami/canvas/p309#xywh=1253,766,312,289",
        "@type": "sc:Canvas",
        "label": "Google Cloud Vision API",
        "metadata": [
            {
                "label": "Text",
                "value": "努力が足りない山のテッペンまで排せ農事試驗場長木村隆木村氏は内務部長に行して大島を観察した、小笠原林業技的も同様大島の際島で沖永良部あたりは大分開拓されておるが他はまだ努力が足りないと思ふ、1、二の島は島民が自棄になつて耕作しないのでないかと思はれる話もある、甑島の如く山のテッペンまでも耕してみるところから見"
            }
        ]
    },
    {
        "@id": "https://github.com/nakamura196/amami/raw/master/docs/iiif/amami/canvas/p309#xywh=1276,1110,254,274",
        "@type": "sc:Canvas",
        "label": "Google Cloud Vision API",
        "metadata": [
            {
                "label": "Text",
                "value": "風土が樹木の成長によい農務課長小笠原鬼此度の旅行は昔は穴から出ては穴に歸る蟹見たいなもので貴は陸に上って観察して夜は日高丸に踊って購るといった具合、內務部長は室海航路を十二、「回りして船には支人以上に強いが吾々はそうでなく、強將の下に弱卒の姿であった陸上は馬で庭々廻ったが此の方は近藤支魅長が得意で威張るし、アダ恐いとて山中は歩かなかったので途に自分は威張る機音もなか"
            }
        ]
    },
    {
        "@id": "https://github.com/nakamura196/amami/raw/master/docs/iiif/amami/canvas/p309#xywh=1357,2327,-12,0",
        "@type": "sc:Canvas",
        "label": "Google Cloud Vision API",
        "metadata": [
            {
                "label": "Text",
                "value": "100"
            }
        ]
    },
    {
        "@id": "https://github.com/nakamura196/amami/raw/master/docs/iiif/amami/canvas/p309#xywh=1275,726,55,14",
        "@type": "sc:Canvas",
        "label": "Google Cloud Vision API",
        "metadata": [
            {
                "label": "Text",
                "value": "[31]"
            }
        ]
    },
    {
        "@id": "https://github.com/nakamura196/amami/raw/master/docs/iiif/amami/canvas/p309#xywh=1302,1429,9,22",
        "@type": "sc:Canvas",
        "label": "Google Cloud Vision API",
        "metadata": [
            {
                "label": "Text",
                "value": "。。。"
            }
        ]
    },
    {
        "@id": "https://github.com/nakamura196/amami/raw/master/docs/iiif/amami/canvas/p309#xywh=1315,2386,-15,0",
        "@type": "sc:Canvas",
        "label": "Google Cloud Vision API",
        "metadata": [
            {
                "label": "Text",
                "value": "(11)"
            }
        ]
    },
    {
        "@id": "https://github.com/nakamura196/amami/raw/master/docs/iiif/amami/canvas/p309#xywh=1262,2024,13,-1",
        "@type": "sc:Canvas",
        "label": "Google Cloud Vision API",
        "metadata": [
            {
                "label": "Text",
                "value": "ob"
            }
        ]
    },
    {
        "@id": "https://github.com/nakamura196/amami/raw/master/docs/iiif/amami/canvas/p309#xywh=1255,2343,19,277",
        "@type": "sc:Canvas",
        "label": "Google Cloud Vision API",
        "metadata": [
            {
                "label": "Text",
                "value": "東京で一番感するのは交通機開と教育機關"
            }
        ]
    },
    {
        "@id": "https://github.com/nakamura196/amami/raw/master/docs/iiif/amami/canvas/p309#xywh=1162,83,69,32",
        "@type": "sc:Canvas",
        "label": "Google Cloud Vision API",
        "metadata": [
            {
                "label": "Text",
                "value": "Red"
            }
        ]
    },
    {
        "@id": "https://github.com/nakamura196/amami/raw/master/docs/iiif/amami/canvas/p309#xywh=1188,3033,36,21",
        "@type": "sc:Canvas",
        "label": "Google Cloud Vision API",
        "metadata": [
            {
                "label": "Text",
                "value": "309"
            }
        ]
    },
    {
        "@id": "https://github.com/nakamura196/amami/raw/master/docs/iiif/amami/canvas/p309#xywh=1194,3454,29,21",
        "@type": "sc:Canvas",
        "label": "Google Cloud Vision API",
        "metadata": [
            {
                "label": "Text",
                "value": "110"
            }
        ]
    },
    {
        "@id": "https://github.com/nakamura196/amami/raw/master/docs/iiif/amami/canvas/p309#xywh=1108,1478,29,118",
        "@type": "sc:Canvas",
        "label": "Google Cloud Vision API",
        "metadata": [
            {
                "label": "Text",
                "value": "鄉土近"
            }
        ]
    },
    {
        "@id": "https://github.com/nakamura196/amami/raw/master/docs/iiif/amami/canvas/p309#xywh=1106,3455,17,19",
        "@type": "sc:Canvas",
        "label": "Google Cloud Vision API",
        "metadata": [
            {
                "label": "Text",
                "value": "19"
            }
        ]
    },
    {
        "@id": "https://github.com/nakamura196/amami/raw/master/docs/iiif/amami/canvas/p309#xywh=1033,1463,51,194",
        "@type": "sc:Canvas",
        "label": "Google Cloud Vision API",
        "metadata": [
            {
                "label": "Text",
                "value": "支廳長嚴重戒告せよと名瀬町會の陳情"
            }
        ]
    },
    {
        "@id": "https://github.com/nakamura196/amami/raw/master/docs/iiif/amami/canvas/p309#xywh=1017,3455,16,21",
        "@type": "sc:Canvas",
        "label": "Google Cloud Vision API",
        "metadata": [
            {
                "label": "Text",
                "value": "18"
            }
        ]
    },
    {
        "@id": "https://github.com/nakamura196/amami/raw/master/docs/iiif/amami/canvas/p309#xywh=942,83,120,33",
        "@type": "sc:Canvas",
        "label": "Google Cloud Vision API",
        "metadata": [
            {
                "label": "Text",
                "value": "Yellow"
            }
        ]
    },
    {
        "@id": "https://github.com/nakamura196/amami/raw/master/docs/iiif/amami/canvas/p309#xywh=857,2002,297,291",
        "@type": "sc:Canvas",
        "label": "Google Cloud Vision API",
        "metadata": [
            {
                "label": "Text",
                "value": "の整備した点である。親町區內幸町円購病院に四旬の籠城生活を続けその屋上遊歩場にて向側の車道の一点をにらみ一分間にその定点を右父は左に通過した薬物の数を数へたるに十五台に及んだ。それで一時間九百台午前五時より午後十一時迄十八時間で一萬六千二円台になる計算である。市内全体では大したものだ。電車、自動車、自薄車、オートバイの右往左往するのは眠がる程である。又､校の勧類と校較も多く學問するのに便利な土地である。"
            }
        ]
    },
    {
        "@id": "https://github.com/nakamura196/amami/raw/master/docs/iiif/amami/canvas/p309#xywh=800,2330,352,295",
        "@type": "sc:Canvas",
        "label": "Google Cloud Vision API",
        "metadata": [
            {
                "label": "Text",
                "value": "一生涯を一つの仕事で通すことはなかなか骨である。非常な才子で風雲に際すれば韓職典薬成数の因をなすことがあるが平凡な人ならば首途の第一歩に於て分に適する厳業を選び一生涯その業務で衣食する方針で進んだ方が結局分相感に出世する。內地でも新民地でもかじりついて政面目に勤めたものが主任とか係長とか課長とか、局長とかいつた様な支配階級になつてをるのを見るが例ある。如何に頭脳明杯な人でも轉々仕事を更へた人はあまり浮んでをらない。仕事に興味を持つてあまり上官に逆はすよい部下を集めて信頼することは一番肝腎だ。"
            }
        ]
    },
    {
        "@id": "https://github.com/nakamura196/amami/raw/master/docs/iiif/amami/canvas/p309#xywh=377,3,785,120",
        "@type": "sc:Canvas",
        "label": "Google Cloud Vision API",
        "metadata": [
            {
                "label": "Text",
                "value": "KodakColorControlPatchesCyan"
            }
        ]
    },
    {
        "@id": "https://github.com/nakamura196/amami/raw/master/docs/iiif/amami/canvas/p309#xywh=415,756,740,299",
        "@type": "sc:Canvas",
        "label": "Google Cloud Vision API",
        "metadata": [
            {
                "label": "Text",
                "value": "(先づ第一に行ったのが玄界島だ、此處は一番先に見たせ1か一番疲弊してある様に思はれた。農業も林業もマダ手をつけないがウントある、山とは云へないかも知れぬが丘陵経きで植林の余地は深山ある、同島に二百年以上を經たと思はれる老杉七十本ばかりが密生してみるところがあつたが、之等の状態を見るに同島の植林は頭る有望である。農耕地も遊んでみるし林地としても遊んでみろよ地が多い。公蘇鐵の葉を陰干しにし、破して外國に解出する工場がある、之は名と兩方にあるが、神戸の東洋木工所の程宮である一年に一萬校入の市が二千個位出るそうで一五十間內外と云ふから十萬回の産績があるワケである。出先さは米図へ五期共他が獨佛の諸國である、之は向ふで装飾用に用いられるのであるから無限に出されるものではなからうが昧盛柴の利用の途があると云ふこと、斯様な副業もあると云ふ強味にはなる、珠城のは現に肥料に用いたり、赤に供せられてみるが、珠城を非畔に植えて防風林とすることは至極有効なこと~思ふ。<第二に大品本島に渡った、名瀬から古仁屋に縦其したが此店は農耕の餘地なしと云つてもよく、全く山林地である、土質も非常にい、樹木もよく成長してあるが、全部が天然"
            }
        ]
    },
    {
        "@id": "https://github.com/nakamura196/amami/raw/master/docs/iiif/amami/canvas/p309#xywh=745,85,104,35",
        "@type": "sc:Canvas",
        "label": "Google Cloud Vision API",
        "metadata": [
            {
                "label": "Text",
                "value": "Green"
            }
        ]
    },
    {
        "@id": "https://github.com/nakamura196/amami/raw/master/docs/iiif/amami/canvas/p309#xywh=409,1086,747,296",
        "@type": "sc:Canvas",
        "label": "Google Cloud Vision API",
        "metadata": [
            {
                "label": "Text",
                "value": "林で琉球松が大部分でシー、タブ、ガシマル、シャリンバイ等の雑木林である、木炭、椎茸等の外燃料用材として伐採されている、國有林で造林をやってみる外造林らしいものは行はれてゐない、國有林からは板椎の鐵道桃木が伐り出されるが住里村が多く、一年に一二萬「産出されるそうだ。公次は徳之島であるが此處旧林の餘地は多い、大島郡中で一番農薬も林薬も達しておるのは沖永良部である、それで生活向きも豊かである様に見えた、就中知名村は郡內第一の植林が普及達しておる、技術員も居て計則的に事業が行はれておる、サンゴ礁の上に鐵筋コンクリートの小學校舎がを放つてめるのも此の村である、最後に渡ったのが奥品で此店は一寸しか観察しなかつたが他の島と同様植林の餘地は多い。◆様に一通り郡內を視察したのであるが、大島の振興事業の第一位はドゥしても植林でなくてはならぬと思つた。之は林業自体としても必要だし、農耕地住宅地保護の上からも何はおいても植林第一で行かねばゥンである、一秒六十米の娘風が吹き荒んではどんな農耕地も荒れよう、先づ農耕地住宅地の防風林を作られねばならぬ、防風林の第一線には阿旦が植えられ栓樹が第二線となり、そして蘇鐵等を植えれは佳い、百合が良いといって"
            }
        ]
    },
    {
        "@id": "https://github.com/nakamura196/amami/raw/master/docs/iiif/amami/canvas/p309#xywh=608,2660,545,295",
        "@type": "sc:Canvas",
        "label": "Google Cloud Vision API",
        "metadata": [
            {
                "label": "Text",
                "value": "必ずしも入食税を固執するものに無之、目的は財源捻出にあるは票番書中に登造物使用料のことを併申しあるに徴しても明かなり以上の事實を綜合して考察するに、支廳道次の措置は其の上下級魔の中縦機關たる本能に反し、故意か感情上よりか進達すべを進達せず、傳達すべきを傳達せざりしは事實にして、支廃長は自己の失態を厳はんが爲め如斯見透た事柄を事實を扮師して一時を糊塗せるものなることは蔽ふべからざる事なり、若し此儘に放置して城みさらっか、に町將來の計画に齟齬を生するのみならず、延て町民の編利を阻害するの結果を將來するの恐れあり、仰き願はくは監督官鹿は成るべく此の機合に事の真相を究め將來斯かる過を再ひせしめざる様厳に戒告を加へられむことを敢て悉おの至りに下地なり右町會満場一致の決議に依り意見書提出候也昭和三年六月十三日名瀬町會議長町長平武雄一"
            }
        ]
    },
    {
        "@id": "https://github.com/nakamura196/amami/raw/master/docs/iiif/amami/canvas/p309#xywh=409,1419,599,298",
        "@type": "sc:Canvas",
        "label": "Google Cloud Vision API",
        "metadata": [
            {
                "label": "Text",
                "value": "英に下村內務部長大島郡視察の際名瀬町は支藤の事務荒陵を部長に訴える店があつたが更に六月三日町酎を開き満場一致を以て別項の決議をなし、町代表者をして下村內務部長に對し同部長沖縄視察より蹄座の途次名瀬港船内に於て非公式に之を手交した。町の公金事項に關する意見書名瀬町現在の総務狀態は疲弊困態を極めつ、あり、速かにこれが根本的改善を加ふるに非されば、破綻円出途に収拾すべからざる結果に陥るのあり、此の見地よりして名瀬町は之れが正教策として財源を捻出して財政の基礎を草間にすると同時に、町民の負握する額を軽減し、併せて産業の振興發展を謀るの目的を以て、先つ名瀬港脚を修築し、海岸線を整理して共同荷揚場を設置し以て水陸の連絡を取り交通を便利ならしむると同時に、一定の使用料を徴収して將來の財源に充つべく夫々計歯を立て、客年三月町會滿場一致の決議に依り之れが旅行認可と同時に其財源として起の認可をも併せて禁調し置きしか、其の後起の件に対しては一万六千七百圓を融通す"
            }
        ]
    },
    {
        "@id": "https://github.com/nakamura196/amami/raw/master/docs/iiif/amami/canvas/p309#xywh=760,2388,14,25",
        "@type": "sc:Canvas",
        "label": "Google Cloud Vision API",
        "metadata": [
            {
                "label": "Text",
                "value": "(五)"
            }
        ]
    },
    {
        "@id": "https://github.com/nakamura196/amami/raw/master/docs/iiif/amami/canvas/p309#xywh=462,2000,329,294",
        "@type": "sc:Canvas",
        "label": "Google Cloud Vision API",
        "metadata": [
            {
                "label": "Text",
                "value": "東京の市況も活氣を呈してをるが大阪もなかなか東京に負けない様だ。東京の生活はキチンとしてをるけれど大阪はだらしがないと大阪の知人が言うてをつた。「大阪の食い倒れ」「京都の何れ二奈良の建て併れ」と昔から決つたものらしいが食物に贅澤する程それだけ活気がある譯だ。阪神地方に部長が雲集してをる相だが風俗や言語に定意して生活したら郡内で殺すよりもましかも知れぬ。しかし郷土を忘れ得越しの金子を使はめ主義の生活様式はあまり感心せない問門に残った雨親や弟妹の生活をも適応する必要がある。"
            }
        ]
    },
    {
        "@id": "https://github.com/nakamura196/amami/raw/master/docs/iiif/amami/canvas/p309#xywh=579,2680,17,112",
        "@type": "sc:Canvas",
        "label": "Google Cloud Vision API",
        "metadata": [
            {
                "label": "Text",
                "value": "下村縣內務部長股"
            }
        ]
    },
    {
        "@id": "https://github.com/nakamura196/amami/raw/master/docs/iiif/amami/canvas/p309#xywh=408,2330,327,293",
        "@type": "sc:Canvas",
        "label": "Google Cloud Vision API",
        "metadata": [
            {
                "label": "Text",
                "value": "近年世相が悪化して不愉快である。余が作中でも首相謀殺未遂事件、台湾不敬事件直訴事件等が頻發して要路者も大困りの醒であつた。治者被治者も少し考えねばならぬ。大學教授から共産主義者が出るのは意外である、｢問の研究と、問の悪用とは別物だ和魂漢才を和魂外才迄城張するのはよいが和魂を滅却するのはよくない、乳食教化も必要だが刑罰も大いに必要だ。少し國粋論者が出て社令を浄化して就きたいのだ。草牟田のク幕にこの文を作る。(六月二十四日)"
            }
        ]
    },
    {
        "@id": "https://github.com/nakamura196/amami/raw/master/docs/iiif/amami/canvas/p309#xywh=505,2706,24,154",
        "@type": "sc:Canvas",
        "label": "Google Cloud Vision API",
        "metadata": [
            {
                "label": "Text",
                "value": "名音郵便局新設"
            }
        ]
    },
    {
        "@id": "https://github.com/nakamura196/amami/raw/master/docs/iiif/amami/canvas/p309#xywh=409,2663,73,291",
        "@type": "sc:Canvas",
        "label": "Google Cloud Vision API",
        "metadata": [
            {
                "label": "Text",
                "value": "大和村大字名音に無集配郵便局を新設し名音局と稱して七月一日より事務を開始されることなつた。"
            }
        ]
    },
    {
        "@id": "https://github.com/nakamura196/amami/raw/master/docs/iiif/amami/canvas/p309#xywh=424,2059,14,27",
        "@type": "sc:Canvas",
        "label": "Google Cloud Vision API",
        "metadata": [
            {
                "label": "Text",
                "value": "(四)"
            }
        ]
    },
    {
        "@id": "https://github.com/nakamura196/amami/raw/master/docs/iiif/amami/canvas/p309#xywh=357,84,98,33",
        "@type": "sc:Canvas",
        "label": "Google Cloud Vision API",
        "metadata": [
            {
                "label": "Text",
                "value": "Blue"
            }
        ]
    },
    {
        "@id": "https://github.com/nakamura196/amami/raw/master/docs/iiif/amami/canvas/p309#xywh=401,3454,20,16",
        "@type": "sc:Canvas",
        "label": "Google Cloud Vision API",
        "metadata": [
            {
                "label": "Text",
                "value": "11"
            }
        ]
    },
    {
        "@id": "https://github.com/nakamura196/amami/raw/master/docs/iiif/amami/canvas/p309#xywh=344,3405,54,17",
        "@type": "sc:Canvas",
        "label": "Google Cloud Vision API",
        "metadata": [
            {
                "label": "Text",
                "value": "inches"
            }
        ]
    },
    {
        "@id": "https://github.com/nakamura196/amami/raw/master/docs/iiif/amami/canvas/p309#xywh=344,3447,28,17",
        "@type": "sc:Canvas",
        "label": "Google Cloud Vision API",
        "metadata": [
            {
                "label": "Text",
                "value": "cm"
            }
        ]
    }
]